aioaerospike/__init__.py
aioaerospike/client.py
aioaerospike/protocol/__init__.py
aioaerospike/protocol/admin.py
aioaerospike/protocol/datatypes.py
aioaerospike/protocol/general.py
aioaerospike/protocol/message.py
aioaerospike-0.1.5.dist-info/LICENSE
aioaerospike-0.1.5.dist-info/WHEEL
aioaerospike-0.1.5.dist-info/METADATA
aioaerospike-0.1.5.dist-info/RECORD
