Metadata-Version: 2.1
Name: aioaerospike
Version: 0.1.5
Summary: Async Pure Python implementation of Aerospike client
Home-page: https://github.com/aviramha/aioaerospike
License: MIT
Keywords: aerospike,database,asyncio,nosql
Author: Aviram Hassan
Author-email: aviramyhassan@gmail.com
Requires-Python: >=3.7,<4.0
Classifier: License :: OSI Approved :: MIT License
Classifier: Programming Language :: Python :: 3
Classifier: Programming Language :: Python :: 3.7
Requires-Dist: bcrypt (>=3.1,<4.0)
Requires-Dist: construct (>=2.9,<3.0)
Requires-Dist: msgpack (>=0.6.2,<0.7.0)
Project-URL: Repository, https://github.com/aviramha/aioaerospike
